Metadata-Version: 1.1
Name: visitor
Version: 0.1.1
Summary: A tiny pythonic visitor implementation.
Home-page: http://github.com/mbr/visitor
Author: Marc Brinkmann
Author-email: git@marcbrinkmann.de
License: MIT
Platform: UNKNOWN
Classifier: Programming Language :: Python :: 2
Classifier: Programming Language :: Python :: 3
